mirdip_client/__init__.py
mirdip_client/cli.py
mirdip_client/http.py
mirdip_client-0.1.0.dist-info/licenses/LICENSE
mirdip_client-0.1.0.dist-info/METADATA
mirdip_client-0.1.0.dist-info/WHEEL
mirdip_client-0.1.0.dist-info/entry_points.txt
mirdip_client-0.1.0.dist-info/top_level.txt
mirdip_client-0.1.0.dist-info/RECORD
