Metadata-Version: 2.4
Name: mirdip-client
Version: 0.1.0
Summary: Typed Python client and CLI for mirDIP HTTP API
Author: mirDIP Contributors
License: MIT
Keywords: mirDIP,microRNA,bioinformatics,API,client
Classifier: Programming Language :: Python :: 3
Classifier: License :: OSI Approved :: MIT License
Classifier: Topic :: Scientific/Engineering :: Bio-Informatics
Classifier: Intended Audience :: Science/Research
Classifier: Environment :: Console
Requires-Python: >=3.8
License-File: LICENSE
Provides-Extra: dev
Requires-Dist: black>=24.0; extra == "dev"
Requires-Dist: isort>=5.12; extra == "dev"
Provides-Extra: test
Requires-Dist: pytest>=7.4; extra == "test"
Provides-Extra: docs
Requires-Dist: mkdocs>=1.5; extra == "docs"
Dynamic: license-file
